{
  "faceSize": 32,
  "generatedAt": "2026-04-24T14:17:57.181Z",
  "mazeId": "maze-004",
  "probeCount": 49,
  "probes": [
    {
      "coefficients": [
        [
          0.002671262838346296,
          0.00265227363774815,
          0.002666569465702741
        ],
        [
          0.0006825385482340567,
          0.0006673421348264509,
          0.0006556897154111758
        ],
        [
          0.0018595869185355448,
          0.0018477989058909377,
          0.0018702476983328698
        ],
        [
          0.00031726100781279387,
          0.00031952791992180855,
          0.00032300573992347494
        ]
      ],
      "depthFaces": [
        "maze-004/reflection-probes/probe-000-depth-face-0.png",
        "maze-004/reflection-probes/probe-000-depth-face-1.png",
        "maze-004/reflection-probes/probe-000-depth-face-2.png",
        "maze-004/reflection-probes/probe-000-depth-face-3.png",
        "maze-004/reflection-probes/probe-000-depth-face-4.png",
        "maze-004/reflection-probes/probe-000-depth-face-5.png"
      ],
      "index": 0,
      "processedCubeUvRgbE": "maze-004/reflection-probes/probe-000-processed-cubeuv-rgbe.png",
      "textureHeight": 128,
      "textureWidth": 336
    },
    {
      "coefficients": [
        [
          0.0028093449477420603,
          0.0027817721617364468,
          0.0027892325258991155
        ],
        [
          0.0002961841453032643,
          0.0002709411246269211,
          0.00024614516237482774
        ],
        [
          0.0017899093212590095,
          0.0017808681089809327,
          0.0018051193633124047
        ],
        [
          -0.00009561069554337039,
          -0.00008823521992118871,
          -0.00008303174254042043
        ]
      ],
      "depthFaces": [
        "maze-004/reflection-probes/probe-001-depth-face-0.png",
        "maze-004/reflection-probes/probe-001-depth-face-1.png",
        "maze-004/reflection-probes/probe-001-depth-face-2.png",
        "maze-004/reflection-probes/probe-001-depth-face-3.png",
        "maze-004/reflection-probes/probe-001-depth-face-4.png",
        "maze-004/reflection-probes/probe-001-depth-face-5.png"
      ],
      "index": 1,
      "processedCubeUvRgbE": "maze-004/reflection-probes/probe-001-processed-cubeuv-rgbe.png",
      "textureHeight": 128,
      "textureWidth": 336
    },
    {
      "coefficients": [
        [
          0.003157861307348255,
          0.0031221405610186246,
          0.003123275255431556
        ],
        [
          0.0002104520022708743,
          0.00019369447981486016,
          0.00017748253655287761
        ],
        [
          0.001551897959018294,
          0.0015475335836852937,
          0.0015743813631673798
        ],
        [
          -0.0007082973453319848,
          -0.0006834358241782169,
          -0.0006644440785620746
        ]
      ],
      "depthFaces": [
        "maze-004/reflection-probes/probe-002-depth-face-0.png",
        "maze-004/reflection-probes/probe-002-depth-face-1.png",
        "maze-004/reflection-probes/probe-002-depth-face-2.png",
        "maze-004/reflection-probes/probe-002-depth-face-3.png",
        "maze-004/reflection-probes/probe-002-depth-face-4.png",
        "maze-004/reflection-probes/probe-002-depth-face-5.png"
      ],
      "index": 2,
      "processedCubeUvRgbE": "maze-004/reflection-probes/probe-002-processed-cubeuv-rgbe.png",
      "textureHeight": 128,
      "textureWidth": 336
    },
    {
      "coefficients": [
        [
          0.0027482394890880712,
          0.0027278289581441416,
          0.0027412495357873974
        ],
        [
          0.0001265372715549854,
          0.00011399993156696184,
          0.00010052456999511307
        ],
        [
          0.0018119506473319607,
          0.0018016612596488488,
          0.0018251160903175285
        ],
        [
          -0.00010016175542688246,
          -0.00009883865532958867,
          -0.00009912934565325719
        ]
      ],
      "depthFaces": [
        "maze-004/reflection-probes/probe-003-depth-face-0.png",
        "maze-004/reflection-probes/probe-003-depth-face-1.png",
        "maze-004/reflection-probes/probe-003-depth-face-2.png",
        "maze-004/reflection-probes/probe-003-depth-face-3.png",
        "maze-004/reflection-probes/probe-003-depth-face-4.png",
        "maze-004/reflection-probes/probe-003-depth-face-5.png"
      ],
      "index": 3,
      "processedCubeUvRgbE": "maze-004/reflection-probes/probe-003-processed-cubeuv-rgbe.png",
      "textureHeight": 128,
      "textureWidth": 336
    },
    {
      "coefficients": [
        [
          0.002707059855007828,
          0.0026872106806750343,
          0.002701088652831596
        ],
        [
          0.00019296482498175528,
          0.00017965134327230207,
          0.000165776821218216
        ],
        [
          0.001832101193761928,
          0.0018216849844202839,
          0.0018451097428000167
        ],
        [
          -0.000056120523281325705,
          -0.00005567013704789256,
          -0.000056699845774417875
        ]
      ],
      "depthFaces": [
        "maze-004/reflection-probes/probe-004-depth-face-0.png",
        "maze-004/reflection-probes/probe-004-depth-face-1.png",
        "maze-004/reflection-probes/probe-004-depth-face-2.png",
        "maze-004/reflection-probes/probe-004-depth-face-3.png",
        "maze-004/reflection-probes/probe-004-depth-face-4.png",
        "maze-004/reflection-probes/probe-004-depth-face-5.png"
      ],
      "index": 4,
      "processedCubeUvRgbE": "maze-004/reflection-probes/probe-004-processed-cubeuv-rgbe.png",
      "textureHeight": 128,
      "textureWidth": 336
    },
    {
      "coefficients": [
        [
          0.12676348997619002,
          0.023384814437126582,
          0.0027518976853572676
        ],
        [
          0.008623223799477647,
          0.0015859901000992453,
          0.00017385347313065576
        ],
        [
          -0.025844669732827466,
          -0.002796624248231601,
          0.0018299281103649472
        ],
        [
          -0.08519483999657661,
          -0.014023852333420881,
          0.000020652586934413785
        ]
      ],
      "depthFaces": [
        "maze-004/reflection-probes/probe-005-depth-face-0.png",
        "maze-004/reflection-probes/probe-005-depth-face-1.png",
        "maze-004/reflection-probes/probe-005-depth-face-2.png",
        "maze-004/reflection-probes/probe-005-depth-face-3.png",
        "maze-004/reflection-probes/probe-005-depth-face-4.png",
        "maze-004/reflection-probes/probe-005-depth-face-5.png"
      ],
      "index": 5,
      "processedCubeUvRgbE": "maze-004/reflection-probes/probe-005-processed-cubeuv-rgbe.png",
      "textureHeight": 128,
      "textureWidth": 336
    },
    {
      "coefficients": [
        [
          0.18416387937290674,
          0.03254466680878952,
          0.0026395922896419333
        ],
        [
          0.034414776553551386,
          0.005384637366982593,
          -0.0003146312274152694
        ],
        [
          -0.033429397694099416,
          -0.003995222765865594,
          0.0019079088815880392
        ],
        [
          0.038004255392325166,
          0.006151948192422851,
          0.0003196749256227169
        ]
      ],
      "depthFaces": [
        "maze-004/reflection-probes/probe-006-depth-face-0.png",
        "maze-004/reflection-probes/probe-006-depth-face-1.png",
        "maze-004/reflection-probes/probe-006-depth-face-2.png",
        "maze-004/reflection-probes/probe-006-depth-face-3.png",
        "maze-004/reflection-probes/probe-006-depth-face-4.png",
        "maze-004/reflection-probes/probe-006-depth-face-5.png"
      ],
      "index": 6,
      "processedCubeUvRgbE": "maze-004/reflection-probes/probe-006-processed-cubeuv-rgbe.png",
      "textureHeight": 128,
      "textureWidth": 336
    },
    {
      "coefficients": [
        [
          0.12394514198467331,
          0.022829096712280214,
          0.0026775013810764596
        ],
        [
          -0.023709205281446946,
          -0.003453581953173822,
          0.00064787460169354
        ],
        [
          -0.021171609610654736,
          -0.0020121451270586513,
          0.001874796906478819
        ],
        [
          -0.033065699458986325,
          -0.005978638632483114,
          -0.00046130270525955905
        ]
      ],
      "depthFaces": [
        "maze-004/reflection-probes/probe-007-depth-face-0.png",
        "maze-004/reflection-probes/probe-007-depth-face-1.png",
        "maze-004/reflection-probes/probe-007-depth-face-2.png",
        "maze-004/reflection-probes/probe-007-depth-face-3.png",
        "maze-004/reflection-probes/probe-007-depth-face-4.png",
        "maze-004/reflection-probes/probe-007-depth-face-5.png"
      ],
      "index": 7,
      "processedCubeUvRgbE": "maze-004/reflection-probes/probe-007-processed-cubeuv-rgbe.png",
      "textureHeight": 128,
      "textureWidth": 336
    },
    {
      "coefficients": [
        [
          0.17518716516605726,
          0.031070526242767432,
          0.002716635495963688
        ],
        [
          0.08831516640941067,
          0.014216626374414093,
          0.0001548831139246925
        ],
        [
          -0.012319843927714529,
          -0.0005925967821152252,
          0.0018319717233183396
        ],
        [
          -0.08428089665333284,
          -0.013992976991062752,
          -0.00008459005960972234
        ]
      ],
      "depthFaces": [
        "maze-004/reflection-probes/probe-008-depth-face-0.png",
        "maze-004/reflection-probes/probe-008-depth-face-1.png",
        "maze-004/reflection-probes/probe-008-depth-face-2.png",
        "maze-004/reflection-probes/probe-008-depth-face-3.png",
        "maze-004/reflection-probes/probe-008-depth-face-4.png",
        "maze-004/reflection-probes/probe-008-depth-face-5.png"
      ],
      "index": 8,
      "processedCubeUvRgbE": "maze-004/reflection-probes/probe-008-processed-cubeuv-rgbe.png",
      "textureHeight": 128,
      "textureWidth": 336
    },
    {
      "coefficients": [
        [
          0.2927700648548997,
          0.05065692927854528,
          0.0026957419706966435
        ],
        [
          0.18692252674460516,
          0.03077026170822853,
          0.00016318078610062515
        ],
        [
          -0.034483882902677905,
          -0.004368080044087218,
          0.0018463599064532424
        ],
        [
          -0.09590626336683278,
          -0.01579250589006521,
          -0.00005777820740727261
        ]
      ],
      "depthFaces": [
        "maze-004/reflection-probes/probe-009-depth-face-0.png",
        "maze-004/reflection-probes/probe-009-depth-face-1.png",
        "maze-004/reflection-probes/probe-009-depth-face-2.png",
        "maze-004/reflection-probes/probe-009-depth-face-3.png",
        "maze-004/reflection-probes/probe-009-depth-face-4.png",
        "maze-004/reflection-probes/probe-009-depth-face-5.png"
      ],
      "index": 9,
      "processedCubeUvRgbE": "maze-004/reflection-probes/probe-009-processed-cubeuv-rgbe.png",
      "textureHeight": 128,
      "textureWidth": 336
    },
    {
      "coefficients": [
        [
          1.4981162507702126,
          0.24774421295824586,
          0.002696006979393447
        ],
        [
          0.037155299518483106,
          0.007022829988955459,
          0.00017424870673138327
        ],
        [
          -0.06868625679057075,
          -0.009688237507156782,
          0.0018462685331023174
        ],
        [
          -1.8883041686185995,
          -0.3100731539294812,
          -0.00005489586881266242
        ]
      ],
      "depthFaces": [
        "maze-004/reflection-probes/probe-010-depth-face-0.png",
        "maze-004/reflection-probes/probe-010-depth-face-1.png",
        "maze-004/reflection-probes/probe-010-depth-face-2.png",
        "maze-004/reflection-probes/probe-010-depth-face-3.png",
        "maze-004/reflection-probes/probe-010-depth-face-4.png",
        "maze-004/reflection-probes/probe-010-depth-face-5.png"
      ],
      "index": 10,
      "processedCubeUvRgbE": "maze-004/reflection-probes/probe-010-processed-cubeuv-rgbe.png",
      "textureHeight": 128,
      "textureWidth": 336
    },
    {
      "coefficients": [
        [
          0.36584754724965207,
          0.06273019394312737,
          0.002709282516879522
        ],
        [
          -0.12351402334473326,
          -0.019933568654061522,
          0.0001825898488591245
        ],
        [
          -0.040172016139630354,
          -0.005375947530349781,
          0.0018342341568882978
        ],
        [
          -0.08961607253954429,
          -0.014739058741165146,
          -0.000025885895569653227
        ]
      ],
      "depthFaces": [
        "maze-004/reflection-probes/probe-011-depth-face-0.png",
        "maze-004/reflection-probes/probe-011-depth-face-1.png",
        "maze-004/reflection-probes/probe-011-depth-face-2.png",
        "maze-004/reflection-probes/probe-011-depth-face-3.png",
        "maze-004/reflection-probes/probe-011-depth-face-4.png",
        "maze-004/reflection-probes/probe-011-depth-face-5.png"
      ],
      "index": 11,
      "processedCubeUvRgbE": "maze-004/reflection-probes/probe-011-processed-cubeuv-rgbe.png",
      "textureHeight": 128,
      "textureWidth": 336
    },
    {
      "coefficients": [
        [
          0.4378063631171556,
          0.0739471582121679,
          0.002639653296675274
        ],
        [
          -0.005357269442768821,
          -0.0009988757848523762,
          -0.0003368388261338095
        ],
        [
          -0.03953765658476795,
          -0.0051263384250581304,
          0.0018901990339594873
        ],
        [
          0.13998869947759107,
          0.022301923852059227,
          0.0003289355630021105
        ]
      ],
      "depthFaces": [
        "maze-004/reflection-probes/probe-012-depth-face-0.png",
        "maze-004/reflection-probes/probe-012-depth-face-1.png",
        "maze-004/reflection-probes/probe-012-depth-face-2.png",
        "maze-004/reflection-probes/probe-012-depth-face-3.png",
        "maze-004/reflection-probes/probe-012-depth-face-4.png",
        "maze-004/reflection-probes/probe-012-depth-face-5.png"
      ],
      "index": 12,
      "processedCubeUvRgbE": "maze-004/reflection-probes/probe-012-processed-cubeuv-rgbe.png",
      "textureHeight": 128,
      "textureWidth": 336
    },
    {
      "coefficients": [
        [
          0.272111009280799,
          0.047162098684886765,
          0.0026018468386871155
        ],
        [
          0.05686909459958396,
          0.00935588965058189,
          0.00010589739179318284
        ],
        [
          -0.043129512869808886,
          -0.005793878190481913,
          0.0019316364728619348
        ],
        [
          0.14684319427141362,
          0.02372198360763536,
          -0.00010383701156555239
        ]
      ],
      "depthFaces": [
        "maze-004/reflection-probes/probe-013-depth-face-0.png",
        "maze-004/reflection-probes/probe-013-depth-face-1.png",
        "maze-004/reflection-probes/probe-013-depth-face-2.png",
        "maze-004/reflection-probes/probe-013-depth-face-3.png",
        "maze-004/reflection-probes/probe-013-depth-face-4.png",
        "maze-004/reflection-probes/probe-013-depth-face-5.png"
      ],
      "index": 13,
      "processedCubeUvRgbE": "maze-004/reflection-probes/probe-013-processed-cubeuv-rgbe.png",
      "textureHeight": 128,
      "textureWidth": 336
    },
    {
      "coefficients": [
        [
          0.2535550161411988,
          0.04396285110364127,
          0.0025596106106197977
        ],
        [
          -0.05374942228473723,
          -0.008214108986357771,
          0.0006245232841141815
        ],
        [
          -0.0505524265602846,
          -0.006924865084696767,
          0.0019456808663517724
        ],
        [
          -0.02469167752104769,
          -0.004316443731489156,
          0.00017351789403869698
        ]
      ],
      "depthFaces": [
        "maze-004/reflection-probes/probe-014-depth-face-0.png",
        "maze-004/reflection-probes/probe-014-depth-face-1.png",
        "maze-004/reflection-probes/probe-014-depth-face-2.png",
        "maze-004/reflection-probes/probe-014-depth-face-3.png",
        "maze-004/reflection-probes/probe-014-depth-face-4.png",
        "maze-004/reflection-probes/probe-014-depth-face-5.png"
      ],
      "index": 14,
      "processedCubeUvRgbE": "maze-004/reflection-probes/probe-014-processed-cubeuv-rgbe.png",
      "textureHeight": 128,
      "textureWidth": 336
    },
    {
      "coefficients": [
        [
          0.22662791127215684,
          0.03967059760676163,
          0.0027109212632599015
        ],
        [
          -0.055025371900904875,
          -0.00881345556243166,
          0.00017856891774729357
        ],
        [
          -0.024336889182080722,
          -0.0025981927350854353,
          0.0018364679918048783
        ],
        [
          -0.05471613971074969,
          -0.00919717723583431,
          -0.000034066638999590595
        ]
      ],
      "depthFaces": [
        "maze-004/reflection-probes/probe-015-depth-face-0.png",
        "maze-004/reflection-probes/probe-015-depth-face-1.png",
        "maze-004/reflection-probes/probe-015-depth-face-2.png",
        "maze-004/reflection-probes/probe-015-depth-face-3.png",
        "maze-004/reflection-probes/probe-015-depth-face-4.png",
        "maze-004/reflection-probes/probe-015-depth-face-5.png"
      ],
      "index": 15,
      "processedCubeUvRgbE": "maze-004/reflection-probes/probe-015-processed-cubeuv-rgbe.png",
      "textureHeight": 128,
      "textureWidth": 336
    },
    {
      "coefficients": [
        [
          0.19322119294224183,
          0.03419446555987623,
          0.002753953401696536
        ],
        [
          0.05119307947637658,
          0.008311663393263969,
          0.00021723702341389006
        ],
        [
          -0.01817115391656422,
          -0.0016325012389924584,
          0.001822770972999726
        ],
        [
          -0.09337222371925556,
          -0.015400142809131134,
          0.000008343066804880519
        ]
      ],
      "depthFaces": [
        "maze-004/reflection-probes/probe-016-depth-face-0.png",
        "maze-004/reflection-probes/probe-016-depth-face-1.png",
        "maze-004/reflection-probes/probe-016-depth-face-2.png",
        "maze-004/reflection-probes/probe-016-depth-face-3.png",
        "maze-004/reflection-probes/probe-016-depth-face-4.png",
        "maze-004/reflection-probes/probe-016-depth-face-5.png"
      ],
      "index": 16,
      "processedCubeUvRgbE": "maze-004/reflection-probes/probe-016-processed-cubeuv-rgbe.png",
      "textureHeight": 128,
      "textureWidth": 336
    },
    {
      "coefficients": [
        [
          0.41842810623171456,
          0.07092837080934823,
          0.002960712513229935
        ],
        [
          0.07027402212738602,
          0.011352054000573516,
          0.00016397158091100174
        ],
        [
          -0.03960197804409577,
          -0.005476248682170172,
          0.001631444085511832
        ],
        [
          0.02811323652652878,
          0.0048131491224114075,
          0.0003130795115776299
        ]
      ],
      "depthFaces": [
        "maze-004/reflection-probes/probe-017-depth-face-0.png",
        "maze-004/reflection-probes/probe-017-depth-face-1.png",
        "maze-004/reflection-probes/probe-017-depth-face-2.png",
        "maze-004/reflection-probes/probe-017-depth-face-3.png",
        "maze-004/reflection-probes/probe-017-depth-face-4.png",
        "maze-004/reflection-probes/probe-017-depth-face-5.png"
      ],
      "index": 17,
      "processedCubeUvRgbE": "maze-004/reflection-probes/probe-017-processed-cubeuv-rgbe.png",
      "textureHeight": 128,
      "textureWidth": 336
    },
    {
      "coefficients": [
        [
          0.45488525195895607,
          0.07666684559271696,
          0.0027482337547699285
        ],
        [
          0.0939774150626031,
          0.01536607697555865,
          0.00012892695765230603
        ],
        [
          -0.04810903346144187,
          -0.006764497897969741,
          0.0018129797218445092
        ],
        [
          -0.02325242231953092,
          -0.003500924880107776,
          -0.00005288711732793579
        ]
      ],
      "depthFaces": [
        "maze-004/reflection-probes/probe-018-depth-face-0.png",
        "maze-004/reflection-probes/probe-018-depth-face-1.png",
        "maze-004/reflection-probes/probe-018-depth-face-2.png",
        "maze-004/reflection-probes/probe-018-depth-face-3.png",
        "maze-004/reflection-probes/probe-018-depth-face-4.png",
        "maze-004/reflection-probes/probe-018-depth-face-5.png"
      ],
      "index": 18,
      "processedCubeUvRgbE": "maze-004/reflection-probes/probe-018-processed-cubeuv-rgbe.png",
      "textureHeight": 128,
      "textureWidth": 336
    },
    {
      "coefficients": [
        [
          1.6110874041128975,
          0.26525854149406997,
          0.002662487348498115
        ],
        [
          0.34034394945253954,
          0.05368971924419235,
          -0.00034639987779866476
        ],
        [
          -0.06839150979924091,
          -0.009401106907125433,
          0.0018871834286768674
        ],
        [
          1.9937148069690172,
          0.325395665072455,
          -0.0004642698276489942
        ]
      ],
      "depthFaces": [
        "maze-004/reflection-probes/probe-019-depth-face-0.png",
        "maze-004/reflection-probes/probe-019-depth-face-1.png",
        "maze-004/reflection-probes/probe-019-depth-face-2.png",
        "maze-004/reflection-probes/probe-019-depth-face-3.png",
        "maze-004/reflection-probes/probe-019-depth-face-4.png",
        "maze-004/reflection-probes/probe-019-depth-face-5.png"
      ],
      "index": 19,
      "processedCubeUvRgbE": "maze-004/reflection-probes/probe-019-processed-cubeuv-rgbe.png",
      "textureHeight": 128,
      "textureWidth": 336
    },
    {
      "coefficients": [
        [
          1.4233620223876082,
          0.234816477578875,
          0.0025905784636575868
        ],
        [
          1.7898268391762122,
          0.2929698424628799,
          0.00013862353088907138
        ],
        [
          -0.08121853926970618,
          -0.011668540431745983,
          0.0019443680633791755
        ],
        [
          0.014424385916455168,
          0.0028145764855251857,
          -0.0000883632466161994
        ]
      ],
      "depthFaces": [
        "maze-004/reflection-probes/probe-020-depth-face-0.png",
        "maze-004/reflection-probes/probe-020-depth-face-1.png",
        "maze-004/reflection-probes/probe-020-depth-face-2.png",
        "maze-004/reflection-probes/probe-020-depth-face-3.png",
        "maze-004/reflection-probes/probe-020-depth-face-4.png",
        "maze-004/reflection-probes/probe-020-depth-face-5.png"
      ],
      "index": 20,
      "processedCubeUvRgbE": "maze-004/reflection-probes/probe-020-processed-cubeuv-rgbe.png",
      "textureHeight": 128,
      "textureWidth": 336
    },
    {
      "coefficients": [
        [
          1.5248150602461736,
          0.2515680103887982,
          0.0025613252082222248
        ],
        [
          -2.024536523206484,
          -0.33054201602440464,
          0.0006304715849990169
        ],
        [
          -0.08926171090620043,
          -0.013026362516895275,
          0.0019495224248573461
        ],
        [
          0.2821412793108479,
          0.044346385229450606,
          -0.0002925047820983292
        ]
      ],
      "depthFaces": [
        "maze-004/reflection-probes/probe-021-depth-face-0.png",
        "maze-004/reflection-probes/probe-021-depth-face-1.png",
        "maze-004/reflection-probes/probe-021-depth-face-2.png",
        "maze-004/reflection-probes/probe-021-depth-face-3.png",
        "maze-004/reflection-probes/probe-021-depth-face-4.png",
        "maze-004/reflection-probes/probe-021-depth-face-5.png"
      ],
      "index": 21,
      "processedCubeUvRgbE": "maze-004/reflection-probes/probe-021-processed-cubeuv-rgbe.png",
      "textureHeight": 128,
      "textureWidth": 336
    },
    {
      "coefficients": [
        [
          0.43023027174197154,
          0.07318361915038045,
          0.0027133521630663643
        ],
        [
          -0.14292619660116193,
          -0.022462771536480054,
          0.00018258232338443656
        ],
        [
          -0.03631701697464663,
          -0.004802284266987021,
          0.0018269139584530325
        ],
        [
          0.024495645825759242,
          0.003996674968196827,
          -0.00004334173490699106
        ]
      ],
      "depthFaces": [
        "maze-004/reflection-probes/probe-022-depth-face-0.png",
        "maze-004/reflection-probes/probe-022-depth-face-1.png",
        "maze-004/reflection-probes/probe-022-depth-face-2.png",
        "maze-004/reflection-probes/probe-022-depth-face-3.png",
        "maze-004/reflection-probes/probe-022-depth-face-4.png",
        "maze-004/reflection-probes/probe-022-depth-face-5.png"
      ],
      "index": 22,
      "processedCubeUvRgbE": "maze-004/reflection-probes/probe-022-processed-cubeuv-rgbe.png",
      "textureHeight": 128,
      "textureWidth": 336
    },
    {
      "coefficients": [
        [
          0.369144023748248,
          0.06321944643064763,
          0.002641921590989349
        ],
        [
          0.011429218766466853,
          0.0016344948242668304,
          -0.00034051828630600266
        ],
        [
          -0.03465879085934716,
          -0.004484630965340633,
          0.001889418285632942
        ],
        [
          0.11337480659280534,
          0.018489775769189365,
          0.0003275545101260067
        ]
      ],
      "depthFaces": [
        "maze-004/reflection-probes/probe-023-depth-face-0.png",
        "maze-004/reflection-probes/probe-023-depth-face-1.png",
        "maze-004/reflection-probes/probe-023-depth-face-2.png",
        "maze-004/reflection-probes/probe-023-depth-face-3.png",
        "maze-004/reflection-probes/probe-023-depth-face-4.png",
        "maze-004/reflection-probes/probe-023-depth-face-5.png"
      ],
      "index": 23,
      "processedCubeUvRgbE": "maze-004/reflection-probes/probe-023-processed-cubeuv-rgbe.png",
      "textureHeight": 128,
      "textureWidth": 336
    },
    {
      "coefficients": [
        [
          1.5528421358819295,
          0.2559628124028366,
          0.0026536958145500634
        ],
        [
          -1.8012642482758536,
          -0.29551397592445183,
          0.0001483881322001444
        ],
        [
          -0.0801649707716838,
          -0.011609578782824334,
          0.001899305841870408
        ],
        [
          -0.035656245795606625,
          -0.0062644592490951325,
          -0.0001231116450731848
        ]
      ],
      "depthFaces": [
        "maze-004/reflection-probes/probe-024-depth-face-0.png",
        "maze-004/reflection-probes/probe-024-depth-face-1.png",
        "maze-004/reflection-probes/probe-024-depth-face-2.png",
        "maze-004/reflection-probes/probe-024-depth-face-3.png",
        "maze-004/reflection-probes/probe-024-depth-face-4.png",
        "maze-004/reflection-probes/probe-024-depth-face-5.png"
      ],
      "index": 24,
      "processedCubeUvRgbE": "maze-004/reflection-probes/probe-024-processed-cubeuv-rgbe.png",
      "textureHeight": 128,
      "textureWidth": 336
    },
    {
      "coefficients": [
        [
          0.4998511446512598,
          0.08419348405869076,
          0.00257431532650105
        ],
        [
          0.19435257497249628,
          0.03157677711728088,
          0.0006354956579475893
        ],
        [
          -0.059791771525984964,
          -0.008770278568227222,
          0.0019290449162840861
        ],
        [
          -0.011278956528224955,
          -0.0017379185472163544,
          0.00020898007524163502
        ]
      ],
      "depthFaces": [
        "maze-004/reflection-probes/probe-025-depth-face-0.png",
        "maze-004/reflection-probes/probe-025-depth-face-1.png",
        "maze-004/reflection-probes/probe-025-depth-face-2.png",
        "maze-004/reflection-probes/probe-025-depth-face-3.png",
        "maze-004/reflection-probes/probe-025-depth-face-4.png",
        "maze-004/reflection-probes/probe-025-depth-face-5.png"
      ],
      "index": 25,
      "processedCubeUvRgbE": "maze-004/reflection-probes/probe-025-processed-cubeuv-rgbe.png",
      "textureHeight": 128,
      "textureWidth": 336
    },
    {
      "coefficients": [
        [
          1.6087365423237636,
          0.2650852016499872,
          0.002650868330700335
        ],
        [
          2.0430421543063133,
          0.3333567045426119,
          -0.0002921054241237391
        ],
        [
          -0.07051511243198293,
          -0.009901235501365757,
          0.0018807021735684644
        ],
        [
          -0.3020555263764673,
          -0.047419556906446836,
          0.00035197905722186975
        ]
      ],
      "depthFaces": [
        "maze-004/reflection-probes/probe-026-depth-face-0.png",
        "maze-004/reflection-probes/probe-026-depth-face-1.png",
        "maze-004/reflection-probes/probe-026-depth-face-2.png",
        "maze-004/reflection-probes/probe-026-depth-face-3.png",
        "maze-004/reflection-probes/probe-026-depth-face-4.png",
        "maze-004/reflection-probes/probe-026-depth-face-5.png"
      ],
      "index": 26,
      "processedCubeUvRgbE": "maze-004/reflection-probes/probe-026-processed-cubeuv-rgbe.png",
      "textureHeight": 128,
      "textureWidth": 336
    },
    {
      "coefficients": [
        [
          0.27484165611658273,
          0.047644422952401184,
          0.0026020015750379917
        ],
        [
          0.05822205537785266,
          0.00963884372132203,
          0.00011502797832778457
        ],
        [
          -0.042085151106483684,
          -0.005623129595257043,
          0.0019333403616189856
        ],
        [
          -0.1502476057146139,
          -0.024404205172449307,
          -0.00006695136022815865
        ]
      ],
      "depthFaces": [
        "maze-004/reflection-probes/probe-027-depth-face-0.png",
        "maze-004/reflection-probes/probe-027-depth-face-1.png",
        "maze-004/reflection-probes/probe-027-depth-face-2.png",
        "maze-004/reflection-probes/probe-027-depth-face-3.png",
        "maze-004/reflection-probes/probe-027-depth-face-4.png",
        "maze-004/reflection-probes/probe-027-depth-face-5.png"
      ],
      "index": 27,
      "processedCubeUvRgbE": "maze-004/reflection-probes/probe-027-processed-cubeuv-rgbe.png",
      "textureHeight": 128,
      "textureWidth": 336
    },
    {
      "coefficients": [
        [
          0.372152291498072,
          0.06357284955799021,
          0.0026457707265225153
        ],
        [
          -0.040109836721903463,
          -0.006115737226590232,
          0.0006137019650187984
        ],
        [
          -0.05621971560425445,
          -0.007999305315846368,
          0.0018852348859421514
        ],
        [
          0.1090793784574541,
          0.017792783080940757,
          0.00030892204176169864
        ]
      ],
      "depthFaces": [
        "maze-004/reflection-probes/probe-028-depth-face-0.png",
        "maze-004/reflection-probes/probe-028-depth-face-1.png",
        "maze-004/reflection-probes/probe-028-depth-face-2.png",
        "maze-004/reflection-probes/probe-028-depth-face-3.png",
        "maze-004/reflection-probes/probe-028-depth-face-4.png",
        "maze-004/reflection-probes/probe-028-depth-face-5.png"
      ],
      "index": 28,
      "processedCubeUvRgbE": "maze-004/reflection-probes/probe-028-processed-cubeuv-rgbe.png",
      "textureHeight": 128,
      "textureWidth": 336
    },
    {
      "coefficients": [
        [
          0.42074811717355026,
          0.07131893106438421,
          0.002731915822087814
        ],
        [
          0.12718021113566066,
          0.020249741955337738,
          0.0001564551125325415
        ],
        [
          -0.03310934694437832,
          -0.0042630863369620105,
          0.0018178618939178317
        ],
        [
          0.07478574865890067,
          0.012003301432110158,
          -0.00005348951992478253
        ]
      ],
      "depthFaces": [
        "maze-004/reflection-probes/probe-029-depth-face-0.png",
        "maze-004/reflection-probes/probe-029-depth-face-1.png",
        "maze-004/reflection-probes/probe-029-depth-face-2.png",
        "maze-004/reflection-probes/probe-029-depth-face-3.png",
        "maze-004/reflection-probes/probe-029-depth-face-4.png",
        "maze-004/reflection-probes/probe-029-depth-face-5.png"
      ],
      "index": 29,
      "processedCubeUvRgbE": "maze-004/reflection-probes/probe-029-processed-cubeuv-rgbe.png",
      "textureHeight": 128,
      "textureWidth": 336
    },
    {
      "coefficients": [
        [
          1.5682831700712125,
          0.2585134682608534,
          0.0026612903211211602
        ],
        [
          2.0243435465921493,
          0.33023720063937234,
          -0.000344342909174342
        ],
        [
          -0.05923060407242074,
          -0.007854566675110523,
          0.001887330821573394
        ],
        [
          0.312772928364107,
          0.050284022321159194,
          -0.00046433695983777375
        ]
      ],
      "depthFaces": [
        "maze-004/reflection-probes/probe-030-depth-face-0.png",
        "maze-004/reflection-probes/probe-030-depth-face-1.png",
        "maze-004/reflection-probes/probe-030-depth-face-2.png",
        "maze-004/reflection-probes/probe-030-depth-face-3.png",
        "maze-004/reflection-probes/probe-030-depth-face-4.png",
        "maze-004/reflection-probes/probe-030-depth-face-5.png"
      ],
      "index": 30,
      "processedCubeUvRgbE": "maze-004/reflection-probes/probe-030-processed-cubeuv-rgbe.png",
      "textureHeight": 128,
      "textureWidth": 336
    },
    {
      "coefficients": [
        [
          0.42692505004190323,
          0.07228746498251101,
          0.0028201111935131453
        ],
        [
          0.04987470445243434,
          0.0075750623626676,
          0.0004556894967990391
        ],
        [
          -0.031141806208158533,
          -0.0041460275863717585,
          0.0017363652343325778
        ],
        [
          -0.11013648033156777,
          -0.01798855573404346,
          -0.00009294378884219422
        ]
      ],
      "depthFaces": [
        "maze-004/reflection-probes/probe-031-depth-face-0.png",
        "maze-004/reflection-probes/probe-031-depth-face-1.png",
        "maze-004/reflection-probes/probe-031-depth-face-2.png",
        "maze-004/reflection-probes/probe-031-depth-face-3.png",
        "maze-004/reflection-probes/probe-031-depth-face-4.png",
        "maze-004/reflection-probes/probe-031-depth-face-5.png"
      ],
      "index": 31,
      "processedCubeUvRgbE": "maze-004/reflection-probes/probe-031-processed-cubeuv-rgbe.png",
      "textureHeight": 128,
      "textureWidth": 336
    },
    {
      "coefficients": [
        [
          1.6222301713566338,
          0.26692929737671606,
          0.002452710856786268
        ],
        [
          2.0095751454814486,
          0.32859816226140476,
          -0.00014949416975782964
        ],
        [
          -0.08041323443704428,
          -0.01143756531352857,
          0.002028443712346892
        ],
        [
          0.3423451742927429,
          0.055346242118519455,
          -0.0002893741716250644
        ]
      ],
      "depthFaces": [
        "maze-004/reflection-probes/probe-032-depth-face-0.png",
        "maze-004/reflection-probes/probe-032-depth-face-1.png",
        "maze-004/reflection-probes/probe-032-depth-face-2.png",
        "maze-004/reflection-probes/probe-032-depth-face-3.png",
        "maze-004/reflection-probes/probe-032-depth-face-4.png",
        "maze-004/reflection-probes/probe-032-depth-face-5.png"
      ],
      "index": 32,
      "processedCubeUvRgbE": "maze-004/reflection-probes/probe-032-processed-cubeuv-rgbe.png",
      "textureHeight": 128,
      "textureWidth": 336
    },
    {
      "coefficients": [
        [
          0.36030017182930185,
          0.0617046952987258,
          0.0026900536386933126
        ],
        [
          0.008448555243399982,
          0.0017249760124836949,
          0.0005939404821733279
        ],
        [
          -0.03934595410397517,
          -0.005246882718044698,
          0.0018569054253259616
        ],
        [
          -0.1453901871819963,
          -0.02370555946682767,
          -0.0004986898410833123
        ]
      ],
      "depthFaces": [
        "maze-004/reflection-probes/probe-033-depth-face-0.png",
        "maze-004/reflection-probes/probe-033-depth-face-1.png",
        "maze-004/reflection-probes/probe-033-depth-face-2.png",
        "maze-004/reflection-probes/probe-033-depth-face-3.png",
        "maze-004/reflection-probes/probe-033-depth-face-4.png",
        "maze-004/reflection-probes/probe-033-depth-face-5.png"
      ],
      "index": 33,
      "processedCubeUvRgbE": "maze-004/reflection-probes/probe-033-processed-cubeuv-rgbe.png",
      "textureHeight": 128,
      "textureWidth": 336
    },
    {
      "coefficients": [
        [
          0.22833722121848307,
          0.04008326285847693,
          0.0026713887269923823
        ],
        [
          0.02759661647330231,
          0.0041230336210368295,
          -0.00033080575386690904
        ],
        [
          -0.03556525417145366,
          -0.004419700528417525,
          0.00188858369311834
        ],
        [
          -0.04156893721262813,
          -0.0069484804264209115,
          -0.0004900223708569643
        ]
      ],
      "depthFaces": [
        "maze-004/reflection-probes/probe-034-depth-face-0.png",
        "maze-004/reflection-probes/probe-034-depth-face-1.png",
        "maze-004/reflection-probes/probe-034-depth-face-2.png",
        "maze-004/reflection-probes/probe-034-depth-face-3.png",
        "maze-004/reflection-probes/probe-034-depth-face-4.png",
        "maze-004/reflection-probes/probe-034-depth-face-5.png"
      ],
      "index": 34,
      "processedCubeUvRgbE": "maze-004/reflection-probes/probe-034-processed-cubeuv-rgbe.png",
      "textureHeight": 128,
      "textureWidth": 336
    },
    {
      "coefficients": [
        [
          1.551577083866264,
          0.2562607342332289,
          0.002613947754519431
        ],
        [
          -1.7592401402847728,
          -0.2889272512073982,
          0.0001924370189387823
        ],
        [
          -0.09651967174439638,
          -0.014181368901548159,
          0.001921435640260681
        ],
        [
          0.09416213122441111,
          0.01456757600262974,
          -0.00007739745000252154
        ]
      ],
      "depthFaces": [
        "maze-004/reflection-probes/probe-035-depth-face-0.png",
        "maze-004/reflection-probes/probe-035-depth-face-1.png",
        "maze-004/reflection-probes/probe-035-depth-face-2.png",
        "maze-004/reflection-probes/probe-035-depth-face-3.png",
        "maze-004/reflection-probes/probe-035-depth-face-4.png",
        "maze-004/reflection-probes/probe-035-depth-face-5.png"
      ],
      "index": 35,
      "processedCubeUvRgbE": "maze-004/reflection-probes/probe-035-processed-cubeuv-rgbe.png",
      "textureHeight": 128,
      "textureWidth": 336
    },
    {
      "coefficients": [
        [
          0.5073733573107917,
          0.08544635249082802,
          0.0026782407273535963
        ],
        [
          0.0764618282714034,
          0.012741614950456965,
          0.0006090155546264112
        ],
        [
          -0.04612735398111405,
          -0.006478073769389844,
          0.0018570884661552542
        ],
        [
          0.16298288556028676,
          0.026321561448958496,
          0.00036173950439093974
        ]
      ],
      "depthFaces": [
        "maze-004/reflection-probes/probe-036-depth-face-0.png",
        "maze-004/reflection-probes/probe-036-depth-face-1.png",
        "maze-004/reflection-probes/probe-036-depth-face-2.png",
        "maze-004/reflection-probes/probe-036-depth-face-3.png",
        "maze-004/reflection-probes/probe-036-depth-face-4.png",
        "maze-004/reflection-probes/probe-036-depth-face-5.png"
      ],
      "index": 36,
      "processedCubeUvRgbE": "maze-004/reflection-probes/probe-036-processed-cubeuv-rgbe.png",
      "textureHeight": 128,
      "textureWidth": 336
    },
    {
      "coefficients": [
        [
          1.561685277156591,
          0.25768563460864913,
          0.0026501027614954328
        ],
        [
          0.3108291212224294,
          0.05014323268813548,
          -0.00032333677172246357
        ],
        [
          -0.062076190960228324,
          -0.008515970631340257,
          0.0018847324934648478
        ],
        [
          -2.0279360162709046,
          -0.3314259207541912,
          0.0003334740957212391
        ]
      ],
      "depthFaces": [
        "maze-004/reflection-probes/probe-037-depth-face-0.png",
        "maze-004/reflection-probes/probe-037-depth-face-1.png",
        "maze-004/reflection-probes/probe-037-depth-face-2.png",
        "maze-004/reflection-probes/probe-037-depth-face-3.png",
        "maze-004/reflection-probes/probe-037-depth-face-4.png",
        "maze-004/reflection-probes/probe-037-depth-face-5.png"
      ],
      "index": 37,
      "processedCubeUvRgbE": "maze-004/reflection-probes/probe-037-processed-cubeuv-rgbe.png",
      "textureHeight": 128,
      "textureWidth": 336
    },
    {
      "coefficients": [
        [
          0.414106274972662,
          0.07025692152774893,
          0.0026771759247341954
        ],
        [
          0.06489976504525038,
          0.010906956702228411,
          0.0006313823701525023
        ],
        [
          -0.03909323841301291,
          -0.005069929876962743,
          0.0018725499616632432
        ],
        [
          -0.02925684829412234,
          -0.004895192682327949,
          -0.0004800788053626695
        ]
      ],
      "depthFaces": [
        "maze-004/reflection-probes/probe-038-depth-face-0.png",
        "maze-004/reflection-probes/probe-038-depth-face-1.png",
        "maze-004/reflection-probes/probe-038-depth-face-2.png",
        "maze-004/reflection-probes/probe-038-depth-face-3.png",
        "maze-004/reflection-probes/probe-038-depth-face-4.png",
        "maze-004/reflection-probes/probe-038-depth-face-5.png"
      ],
      "index": 38,
      "processedCubeUvRgbE": "maze-004/reflection-probes/probe-038-processed-cubeuv-rgbe.png",
      "textureHeight": 128,
      "textureWidth": 336
    },
    {
      "coefficients": [
        [
          1.525603668617052,
          0.2513902577869074,
          0.002714389836562386
        ],
        [
          0.0020789097465865264,
          0.0010933365751846125,
          0.0001541952428309347
        ],
        [
          -0.0715578235866067,
          -0.010054878900984046,
          0.0018322419657290192
        ],
        [
          -1.6960572926403241,
          -0.27871162250697484,
          -0.00008455299733335471
        ]
      ],
      "depthFaces": [
        "maze-004/reflection-probes/probe-039-depth-face-0.png",
        "maze-004/reflection-probes/probe-039-depth-face-1.png",
        "maze-004/reflection-probes/probe-039-depth-face-2.png",
        "maze-004/reflection-probes/probe-039-depth-face-3.png",
        "maze-004/reflection-probes/probe-039-depth-face-4.png",
        "maze-004/reflection-probes/probe-039-depth-face-5.png"
      ],
      "index": 39,
      "processedCubeUvRgbE": "maze-004/reflection-probes/probe-039-processed-cubeuv-rgbe.png",
      "textureHeight": 128,
      "textureWidth": 336
    },
    {
      "coefficients": [
        [
          0.34520250638401223,
          0.05912958379619811,
          0.0027115508111935976
        ],
        [
          -0.14605222593478923,
          -0.023368805052812306,
          0.00017891038868693123
        ],
        [
          -0.037626474879581664,
          -0.004983354315382204,
          0.0018334534085617524
        ],
        [
          0.08084412043187375,
          0.013014443814728768,
          -0.000027266948445756987
        ]
      ],
      "depthFaces": [
        "maze-004/reflection-probes/probe-040-depth-face-0.png",
        "maze-004/reflection-probes/probe-040-depth-face-1.png",
        "maze-004/reflection-probes/probe-040-depth-face-2.png",
        "maze-004/reflection-probes/probe-040-depth-face-3.png",
        "maze-004/reflection-probes/probe-040-depth-face-4.png",
        "maze-004/reflection-probes/probe-040-depth-face-5.png"
      ],
      "index": 40,
      "processedCubeUvRgbE": "maze-004/reflection-probes/probe-040-processed-cubeuv-rgbe.png",
      "textureHeight": 128,
      "textureWidth": 336
    },
    {
      "coefficients": [
        [
          0.38288242237860337,
          0.06493136780613372,
          0.0026413914474197773
        ],
        [
          -0.00585729178490892,
          -0.0011185820082147094,
          -0.0003315226141115079
        ],
        [
          -0.04328760364247074,
          -0.005749065110930839,
          0.001892551525879152
        ],
        [
          0.244555111035264,
          0.03960408411771873,
          0.0003292830734541102
        ]
      ],
      "depthFaces": [
        "maze-004/reflection-probes/probe-041-depth-face-0.png",
        "maze-004/reflection-probes/probe-041-depth-face-1.png",
        "maze-004/reflection-probes/probe-041-depth-face-2.png",
        "maze-004/reflection-probes/probe-041-depth-face-3.png",
        "maze-004/reflection-probes/probe-041-depth-face-4.png",
        "maze-004/reflection-probes/probe-041-depth-face-5.png"
      ],
      "index": 41,
      "processedCubeUvRgbE": "maze-004/reflection-probes/probe-041-processed-cubeuv-rgbe.png",
      "textureHeight": 128,
      "textureWidth": 336
    },
    {
      "coefficients": [
        [
          0.4945499016406903,
          0.08351105221969841,
          0.0026879710168264816
        ],
        [
          0.11597207031722341,
          0.018966865351369138,
          0.0006434681127023957
        ],
        [
          -0.08436981808723054,
          -0.01283319960458909,
          0.0018706187743770864
        ],
        [
          -0.05905458788636408,
          -0.00992245660455317,
          -0.0004980201603781427
        ]
      ],
      "depthFaces": [
        "maze-004/reflection-probes/probe-042-depth-face-0.png",
        "maze-004/reflection-probes/probe-042-depth-face-1.png",
        "maze-004/reflection-probes/probe-042-depth-face-2.png",
        "maze-004/reflection-probes/probe-042-depth-face-3.png",
        "maze-004/reflection-probes/probe-042-depth-face-4.png",
        "maze-004/reflection-probes/probe-042-depth-face-5.png"
      ],
      "index": 42,
      "processedCubeUvRgbE": "maze-004/reflection-probes/probe-042-processed-cubeuv-rgbe.png",
      "textureHeight": 128,
      "textureWidth": 336
    },
    {
      "coefficients": [
        [
          1.688984466420139,
          0.27821882816053795,
          0.0026726799288147706
        ],
        [
          0.196083264690165,
          0.03028784493620478,
          -0.0002929971293491461
        ],
        [
          -0.09302640293960374,
          -0.01362378671415025,
          0.0018791433356295003
        ],
        [
          1.8814492833690424,
          0.30673029656717726,
          -0.00048701767430954344
        ]
      ],
      "depthFaces": [
        "maze-004/reflection-probes/probe-043-depth-face-0.png",
        "maze-004/reflection-probes/probe-043-depth-face-1.png",
        "maze-004/reflection-probes/probe-043-depth-face-2.png",
        "maze-004/reflection-probes/probe-043-depth-face-3.png",
        "maze-004/reflection-probes/probe-043-depth-face-4.png",
        "maze-004/reflection-probes/probe-043-depth-face-5.png"
      ],
      "index": 43,
      "processedCubeUvRgbE": "maze-004/reflection-probes/probe-043-processed-cubeuv-rgbe.png",
      "textureHeight": 128,
      "textureWidth": 336
    },
    {
      "coefficients": [
        [
          0.33806793088489684,
          0.057346778727683706,
          0.0022784979910457906
        ],
        [
          -0.008110367610877457,
          -0.0010545421484070866,
          0.0003409203140237321
        ],
        [
          -0.046608183294594936,
          -0.006327389294579814,
          0.0016832615560612332
        ],
        [
          -0.1550267083656159,
          -0.02493676847904978,
          -0.00036376105917879933
        ]
      ],
      "depthFaces": [
        "maze-004/reflection-probes/probe-044-depth-face-0.png",
        "maze-004/reflection-probes/probe-044-depth-face-1.png",
        "maze-004/reflection-probes/probe-044-depth-face-2.png",
        "maze-004/reflection-probes/probe-044-depth-face-3.png",
        "maze-004/reflection-probes/probe-044-depth-face-4.png",
        "maze-004/reflection-probes/probe-044-depth-face-5.png"
      ],
      "index": 44,
      "processedCubeUvRgbE": "maze-004/reflection-probes/probe-044-processed-cubeuv-rgbe.png",
      "textureHeight": 128,
      "textureWidth": 336
    },
    {
      "coefficients": [
        [
          0.1744282406364526,
          0.031211536416582388,
          0.002686122005722857
        ],
        [
          -0.005098021027617069,
          -0.0007583615068592237,
          0.00019139424135337105
        ],
        [
          -0.03496419985707215,
          -0.004289532880217902,
          0.0018554977504884284
        ],
        [
          0.08024085587111468,
          0.013136169001270268,
          -0.00009128827277468654
        ]
      ],
      "depthFaces": [
        "maze-004/reflection-probes/probe-045-depth-face-0.png",
        "maze-004/reflection-probes/probe-045-depth-face-1.png",
        "maze-004/reflection-probes/probe-045-depth-face-2.png",
        "maze-004/reflection-probes/probe-045-depth-face-3.png",
        "maze-004/reflection-probes/probe-045-depth-face-4.png",
        "maze-004/reflection-probes/probe-045-depth-face-5.png"
      ],
      "index": 45,
      "processedCubeUvRgbE": "maze-004/reflection-probes/probe-045-processed-cubeuv-rgbe.png",
      "textureHeight": 128,
      "textureWidth": 336
    },
    {
      "coefficients": [
        [
          0.20406747532741404,
          0.03587358644250669,
          0.0026978866684283695
        ],
        [
          0.093076603204615,
          0.01506590173362007,
          0.00017680928553868972
        ],
        [
          -0.027163944100894684,
          -0.0029435682612450574,
          0.0018480057324963717
        ],
        [
          0.08512454151094292,
          0.013952082882677932,
          -0.00005694060406957028
        ]
      ],
      "depthFaces": [
        "maze-004/reflection-probes/probe-046-depth-face-0.png",
        "maze-004/reflection-probes/probe-046-depth-face-1.png",
        "maze-004/reflection-probes/probe-046-depth-face-2.png",
        "maze-004/reflection-probes/probe-046-depth-face-3.png",
        "maze-004/reflection-probes/probe-046-depth-face-4.png",
        "maze-004/reflection-probes/probe-046-depth-face-5.png"
      ],
      "index": 46,
      "processedCubeUvRgbE": "maze-004/reflection-probes/probe-046-processed-cubeuv-rgbe.png",
      "textureHeight": 128,
      "textureWidth": 336
    },
    {
      "coefficients": [
        [
          0.307830569099981,
          0.05301181320441469,
          0.002709900089254275
        ],
        [
          0.22164854114512683,
          0.03615565528447592,
          0.0001851873348272498
        ],
        [
          -0.045000759786320566,
          -0.006172825055256264,
          0.0018364502773843788
        ],
        [
          0.08298058238089248,
          0.013413732155398537,
          -0.00008384710233572995
        ]
      ],
      "depthFaces": [
        "maze-004/reflection-probes/probe-047-depth-face-0.png",
        "maze-004/reflection-probes/probe-047-depth-face-1.png",
        "maze-004/reflection-probes/probe-047-depth-face-2.png",
        "maze-004/reflection-probes/probe-047-depth-face-3.png",
        "maze-004/reflection-probes/probe-047-depth-face-4.png",
        "maze-004/reflection-probes/probe-047-depth-face-5.png"
      ],
      "index": 47,
      "processedCubeUvRgbE": "maze-004/reflection-probes/probe-047-processed-cubeuv-rgbe.png",
      "textureHeight": 128,
      "textureWidth": 336
    },
    {
      "coefficients": [
        [
          1.4975377387509685,
          0.24690363733876072,
          0.002662585917638231
        ],
        [
          0.2602853328608601,
          0.04069735585840651,
          -0.00033493641636594366
        ],
        [
          -0.12999945822040757,
          -0.019463983374676624,
          0.0018922423096261781
        ],
        [
          2.00867725422481,
          0.3280190655564455,
          -0.0004636156310479956
        ]
      ],
      "depthFaces": [
        "maze-004/reflection-probes/probe-048-depth-face-0.png",
        "maze-004/reflection-probes/probe-048-depth-face-1.png",
        "maze-004/reflection-probes/probe-048-depth-face-2.png",
        "maze-004/reflection-probes/probe-048-depth-face-3.png",
        "maze-004/reflection-probes/probe-048-depth-face-4.png",
        "maze-004/reflection-probes/probe-048-depth-face-5.png"
      ],
      "index": 48,
      "processedCubeUvRgbE": "maze-004/reflection-probes/probe-048-processed-cubeuv-rgbe.png",
      "textureHeight": 128,
      "textureWidth": 336
    }
  ]
}