{
  "phases": [
    {
      "durationMs": 4843,
      "label": "reflection-captures"
    },
    {
      "durationMs": 2119,
      "label": "startup"
    },
    {
      "durationMs": 521,
      "label": "debug-controls"
    }
  ],
  "screenshotCount": 0,
  "screenshotMs": 0,
  "startedAt": "2026-04-27T15:05:46.823Z",
  "loadingCompleteAtMs": 1799.9,
  "shellVisibleAtMs": 16.599999994039536,
  "totalRunMs": 7493,
  "finishedAt": "2026-04-27T15:05:54.317Z",
  "totalPhaseMs": 7483,
  "wroteAt": "2026-04-27T15:05:54.317Z"
}