{
  "phases": [
    {
      "durationMs": 35716,
      "label": "startup"
    },
    {
      "durationMs": 8820,
      "label": "volumetric-fog"
    },
    {
      "durationMs": 7334,
      "label": "debug-controls"
    },
    {
      "durationMs": 3265,
      "label": "reflection-captures"
    }
  ],
  "screenshotCount": 1,
  "screenshotMs": 3047,
  "startedAt": "2026-04-19T12:21:42.442Z",
  "totalRunMs": 58201,
  "finishedAt": "2026-04-19T12:22:40.645Z",
  "totalPhaseMs": 55135,
  "wroteAt": "2026-04-19T12:22:40.645Z"
}